Workbook

Sheet Sheet1
A1: symbol | B1: id | C1: name | D1: vlookup | G1: AVAX': 'avalanche-2'
A2: aapl | B2: twin-asset-token-aapl | C2: TWIN ASSET TOKEN AAPL | D2: =VLOOKUP(A2,Sheet2!$A:$B,1,0) -> #N/A
A3: aapl.d | B3: dinari-aapl-dshares | C3: Dinari AAPL | D3: =VLOOKUP(A3,Sheet2!$A:$B,1,0) -> #N/A
A4: aaplx | B4: apple-xstock | C4: Apple xStock | D4: =VLOOKUP(A4,Sheet2!$A:$B,1,0) -> #N/A
A5: aarb | B5: aave-v3-arb | C5: Aave v3 ARB | D5: =VLOOKUP(A5,Sheet2!$A:$B,1,0) -> #N/A
A6: aark | B6: aark-digital | C6: Aark Digital | D6: =VLOOKUP(A6,Sheet2!$A:$B,1,0) -> #N/A
A7: aart | B7: all-art | C7: ALL.ART | D7: =VLOOKUP(A7,Sheet2!$A:$B,1,0) -> #N/A
A8: aast | B8: aastoken | C8: AASToken | D8: =VLOOKUP(A8,Sheet2!$A:$B,1,0) -> #N/A
A9: aave | B9: aave | C9: Aave | D9: =VLOOKUP(A9,Sheet2!$A:$B,1,0) -> AAVE | F9: ="'"&A9&"'"&":"&"'"&B9&"'"&"," -> 'aave':'aave',
A10: aax | B10: academic-labs | C10: Academic Labs | D10: =VLOOKUP(A10,Sheet2!$A:$B,1,0) -> #N/A
A11: ab | B11: arma-block | C11: Arma Block | D11: =VLOOKUP(A11,Sheet2!$A:$B,1,0) -> #N/A
A12: ab | B12: newton-project | C12: AB | D12: =VLOOKUP(A12,Sheet2!$A:$B,1,0) -> #N/A
A13: abal | B13: aave-bal | C13: Aave BAL | D13: =VLOOKUP(A13,Sheet2!$A:$B,1,0) -> #N/A
A14: abal | B14: aave-v3-bal | C14: Aave v3 BAL | D14: =VLOOKUP(A14,Sheet2!$A:$B,1,0) -> #N/A
A15: abal | B15: arch-balanced-portfolio | C15: Arch Balanced Portfolio | D15: =VLOOKUP(A15,Sheet2!$A:$B,1,0) -> #N/A
A16: abasusdbc | B16: aave-v3-usdbc | C16: Aave v3 aBasUSDbC | D16: =VLOOKUP(A16,Sheet2!$A:$B,1,0) -> #N/A
A17: abat | B17: aave-bat | C17: Aave BAT | D17: =VLOOKUP(A17,Sheet2!$A:$B,1,0) -> #N/A
A18: abat | B18: aave-bat-v1 | C18: Aave BAT v1 | D18: =VLOOKUP(A18,Sheet2!$A:$B,1,0) -> #N/A
A19: abax | B19: abax | C19: Abax | D19: =VLOOKUP(A19,Sheet2!$A:$B,1,0) -> #N/A
A20: abbc | B20: alibabacoin | C20: ABBC | D20: =VLOOKUP(A20,Sheet2!$A:$B,1,0) -> #N/A
A21: abbvx | B21: abbvie-xstock | C21: AbbVie xStock | D21: =VLOOKUP(A21,Sheet2!$A:$B,1,0) -> #N/A
... A100: ad | B100: agent-dora | C100: Agent DORA | D100: =VLOOKUP(A100,Sheet2!$A:$B,1,0) -> #N/A
A101: ada | B101: cardano | C101: Cardano | D101: =VLOOKUP(A101,Sheet2!$A:$B,1,0) -> ADA | F101: ="'"&A101&"'"&":"&"'"&B101&"'"&"," -> 'ada':'cardano',
A102: adacash | B102: adacash | C102: ADAcash | D102: =VLOOKUP(A102,Sheet2!$A:$B,1,0) -> #N/A
A103: adai | B103: aave-dai | C103: Aave DAI | D103: =VLOOKUP(A103,Sheet2!$A:$B,1,0) -> #N/A
A104: adai | B104: aave-dai-v1 | C104: Aave DAI v1 | D104: =VLOOKUP(A104,Sheet2!$A:$B,1,0) -> #N/A
A105: adai | B105: aave-v3-dai | C105: Aave v3 DAI | D105: =VLOOKUP(A105,Sheet2!$A:$B,1,0) -> #N/A
A106: adao | B106: adadao | C106: ADADao | D106: =VLOOKUP(A106,Sheet2!$A:$B,1,0) -> #N/A
A107: adapad | B107: adapad | C107: ADAPad | D107: =VLOOKUP(A107,Sheet2!$A:$B,1,0) -> #N/A
A108: adasol | B108: ada-the-dog | C108: ADA | D108: =VLOOKUP(A108,Sheet2!$A:$B,1,0) -> #N/A
A109: adbe.d | B109: dinari-adbe | C109: Dinari ADBE | D109: =VLOOKUP(A109,Sheet2!$A:$B,1,0) -> #N/A
A110: adco | B110: advertise-coin | C110: Advertise Coin | D110: =VLOOKUP(A110,Sheet2!$A:$B,1,0) -> #N/A
A111: add | B111: add-finance | C111: Add Finance | D111: =VLOOKUP(A111,Sheet2!$A:$B,1,0) -> #N/A
A112: addon | B112: addon-ai | C112: AddOn Ai | D112: =VLOOKUP(A112,Sheet2!$A:$B,1,0) -> #N/A
A113: addy | B113: adamant | C113: Adamant | D113: =VLOOKUP(A113,Sheet2!$A:$B,1,0) -> #N/A
... A433: alfa | B433: alfa-society | C433: alfa.society | D433: =VLOOKUP(A433,Sheet2!$A:$B,1,0) -> #N/A
A434: algo | B434: algorand | C434: Algorand | D434: =VLOOKUP(A434,Sheet2!$A:$B,1,0) -> ALGO | F434: ="'"&A434&"'"&":"&"'"&B434&"'"&"," -> 'algo':'algorand',
A435: algoai | B435: algoritha-a-i | C435: Algoritha A.I | D435: =VLOOKUP(A435,Sheet2!$A:$B,1,0) -> #N/A
A436: algt | B436: algotrade | C436: AlgoTrade | D436: =VLOOKUP(A436,Sheet2!$A:$B,1,0) -> #N/A
A437: ali | B437: alethea-artificial-liquid-intelligence-token | C437: Artificial Liquid Intelligence | D437: =VLOOKUP(A437,Sheet2!$A:$B,1,0) -> #N/A
A438: ali | B438: alita | C438: Alita | D438: =VLOOKUP(A438,Sheet2!$A:$B,1,0) -> #N/A
A439: alias | B439: spectrecoin | C439: Alias | D439: =VLOOKUP(A439,Sheet2!$A:$B,1,0) -> #N/A
A440: alice | B440: alice | C440: Alice | D440: =VLOOKUP(A440,Sheet2!$A:$B,1,0) -> #N/A
A441: alice | B441: alice-2 | C441: Alice | D441: =VLOOKUP(A441,Sheet2!$A:$B,1,0) -> #N/A
A442: alice | B442: alice-3 | C442: Alice | D442: =VLOOKUP(A442,Sheet2!$A:$B,1,0) -> #N/A
A443: alice | B443: alice-4 | C443: AdaptLearnIntellectCompanyEngine | D443: =VLOOKUP(A443,Sheet2!$A:$B,1,0) -> #N/A
A444: alice | B444: my-neighbor-alice | C444: My Neighbor Alice | D444: =VLOOKUP(A444,Sheet2!$A:$B,1,0) -> #N/A
A445: alien | B445: alien | C445: Alien | D445: =VLOOKUP(A445,Sheet2!$A:$B,1,0) -> #N/A
A446: alien | B446: alienswap | C446: AlienSwap | D446: =VLOOKUP(A446,Sheet2!$A:$B,1,0) -> #N/A
... A667: apd | B667: apdao | C667: APDAO | D667: =VLOOKUP(A667,Sheet2!$A:$B,1,0) -> #N/A
A668: ape | B668: apecoin | C668: ApeCoin | D668: =VLOOKUP(A668,Sheet2!$A:$B,1,0) -> APE | F668: ="'"&A668&"'"&":"&"'"&B668&"'"&"," -> 'ape':'apecoin',
A669: aped | B669: aped | C669: Aped | D669: =VLOOKUP(A669,Sheet2!$A:$B,1,0) -> #N/A
A670: aped | B670: aped-4 | C670: APED | D670: =VLOOKUP(A670,Sheet2!$A:$B,1,0) -> #N/A
A671: aped | B671: i-aped | C671: i aped | D671: =VLOOKUP(A671,Sheet2!$A:$B,1,0) -> #N/A
A672: apedev | B672: the-dev-is-an-ape | C672: The dev is an Ape | D672: =VLOOKUP(A672,Sheet2!$A:$B,1,0) -> #N/A
A673: apedog | B673: apedog | C673: APEDOG | D673: =VLOOKUP(A673,Sheet2!$A:$B,1,0) -> #N/A
A674: apeman | B674: ape-man | C674: Ape Man | D674: =VLOOKUP(A674,Sheet2!$A:$B,1,0) -> #N/A
A675: apepe | B675: ape-and-pepe | C675: Ape and Pepe | D675: =VLOOKUP(A675,Sheet2!$A:$B,1,0) -> #N/A
A676: apes | B676: apes-2 | C676: APES | D676: =VLOOKUP(A676,Sheet2!$A:$B,1,0) -> #N/A
A677: apes | B677: apescreener | C677: ApeScreener | D677: =VLOOKUP(A677,Sheet2!$A:$B,1,0) -> #N/A
A678: apes | B678: based-degen-apes | C678: Based Degen Apes | D678: =VLOOKUP(A678,Sheet2!$A:$B,1,0) -> #N/A
A679: apes | B679: primeape | C679: PRIMEAPE | D679: =VLOOKUP(A679,Sheet2!$A:$B,1,0) -> #N/A
A680: apet | B680: apejackpot | C680: ApeJackPot | D680: =VLOOKUP(A680,Sheet2!$A:$B,1,0) -> #N/A
... A707: aps | B707: apsis | C707: Apsis | D707: =VLOOKUP(A707,Sheet2!$A:$B,1,0) -> #N/A
A708: apt | B708: aptos | C708: Aptos | D708: =VLOOKUP(A708,Sheet2!$A:$B,1,0) -> APT | F708: ="'"&A708&"'"&":"&"'"&B708&"'"&"," -> 'apt':'aptos',
A709: aptm | B709: apertum | C709: Apertum | D709: =VLOOKUP(A709,Sheet2!$A:$B,1,0) -> #N/A
A710: aptr | B710: aperture-finance | C710: Aperture Finance | D710: =VLOOKUP(A710,Sheet2!$A:$B,1,0) -> #N/A
A711: aptrnk | B711: apptronik-prestocks | C711: Apptronik PreStocks | D711: =VLOOKUP(A711,Sheet2!$A:$B,1,0) -> #N/A
A712: apu | B712: apu-apustaja-sol | C712: Apu Apustaja (Solana) | D712: =VLOOKUP(A712,Sheet2!$A:$B,1,0) -> #N/A
A713: apu | B713: apu-s-club | C713: Apu Apustaja | D713: =VLOOKUP(A713,Sheet2!$A:$B,1,0) -> #N/A
A714: apu | B714: based-apu | C714: Based Apu | D714: =VLOOKUP(A714,Sheet2!$A:$B,1,0) -> #N/A
A715: apuff | B715: airpuff | C715: Airpuff | D715: =VLOOKUP(A715,Sheet2!$A:$B,1,0) -> #N/A
A716: apugurl | B716: apu-gurl | C716: Apu Gurl | D716: =VLOOKUP(A716,Sheet2!$A:$B,1,0) -> #N/A
A717: apw | B717: apwine | C717: Spectra [OLD] | D717: =VLOOKUP(A717,Sheet2!$A:$B,1,0) -> #N/A
A718: apx | B718: apollox-2 | C718: APX | D718: =VLOOKUP(A718,Sheet2!$A:$B,1,0) -> #N/A
A719: apx | B719: appics | C719: Appics | D719: =VLOOKUP(A719,Sheet2!$A:$B,1,0) -> #N/A
A720: apx | B720: astropepex | C720: AstroPepeX | D720: =VLOOKUP(A720,Sheet2!$A:$B,1,0) -> #N/A
... A742: arata | B742: arata-agi | C742: Arata AGI | D742: =VLOOKUP(A742,Sheet2!$A:$B,1,0) -> #N/A
A743: arb | B743: arbitrum | C743: Arbitrum | D743: =VLOOKUP(A743,Sheet2!$A:$B,1,0) -> ARB | F743: ="'"&A743&"'"&":"&"'"&B743&"'"&"," -> 'arb':'arbitrum',
A744: arb.e | B744: bridged-arbitrum-lightlink | C744: Bridged Arbitrum (Lightlink) | D744: =VLOOKUP(A744,Sheet2!$A:$B,1,0) -> #N/A
A745: arbi | B745: arbipad | C745: ArbiPad | D745: =VLOOKUP(A745,Sheet2!$A:$B,1,0) -> #N/A
A746: arbi | B746: arbitrum-ecosystem-index | C746: Arbitrum Ecosystem Index | D746: =VLOOKUP(A746,Sheet2!$A:$B,1,0) -> #N/A
A747: arbinauts | B747: arbinauts | C747: Arbinauts | D747: =VLOOKUP(A747,Sheet2!$A:$B,1,0) -> #N/A
A748: arbs | B748: arbswap | C748: Arbswap | D748: =VLOOKUP(A748,Sheet2!$A:$B,1,0) -> #N/A
A749: arbus | B749: arbus | C749: Arbus | D749: =VLOOKUP(A749,Sheet2!$A:$B,1,0) -> #N/A
A750: arbuz | B750: arbuz | C750: ARBUZ | D750: =VLOOKUP(A750,Sheet2!$A:$B,1,0) -> #N/A
A751: arc | B751: ai-rig-complex | C751: AI Rig Complex | D751: =VLOOKUP(A751,Sheet2!$A:$B,1,0) -> #N/A
A752: arc | B752: arc | C752: Arc | D752: =VLOOKUP(A752,Sheet2!$A:$B,1,0) -> #N/A
A753: arc | B753: arcade-2 | C753: Arcade | D753: =VLOOKUP(A753,Sheet2!$A:$B,1,0) -> #N/A
A754: arc | B754: arcadeum | C754: Arcadeum | D754: =VLOOKUP(A754,Sheet2!$A:$B,1,0) -> #N/A
A755: arc | B755: archly-finance | C755: Archly Finance | D755: =VLOOKUP(A755,Sheet2!$A:$B,1,0) -> #N/A
... A885: aspo | B885: aspo-world | C885: ASPO World | D885: =VLOOKUP(A885,Sheet2!$A:$B,1,0) -> #N/A
A886: asr | B886: as-roma-fan-token | C886: AS Roma Fan Token | D886: =VLOOKUP(A886,Sheet2!$A:$B,1,0) -> ASR | F886: ="'"&A886&"'"&":"&"'"&B886&"'"&"," -> 'asr':'as-roma-fan-token',
A887: asrr | B887: assisterr-ai | C887: Assisterr AI | D887: =VLOOKUP(A887,Sheet2!$A:$B,1,0) -> #N/A
A888: ass | B888: australian-safe-shepherd | C888: Australian Safe Shepherd | D888: =VLOOKUP(A888,Sheet2!$A:$B,1,0) -> #N/A
A889: ass&p 500 | B889: ass-p-500 | C889: ASS&P 500 | D889: =VLOOKUP(A889,Sheet2!$A:$B,1,0) -> #N/A
A890: assai | B890: assai | C890: ASSAI | D890: =VLOOKUP(A890,Sheet2!$A:$B,1,0) -> #N/A
A891: asscoin | B891: asscoin | C891: ASSCOIN | D891: =VLOOKUP(A891,Sheet2!$A:$B,1,0) -> #N/A
A892: assdaq | B892: assdaq | C892: ASSDAQ | D892: =VLOOKUP(A892,Sheet2!$A:$B,1,0) -> #N/A
A893: asset | B893: asset-chain | C893: Asset | D893: =VLOOKUP(A893,Sheet2!$A:$B,1,0) -> #N/A
...

Sheet Sheet2
A1: Ticker
A2: AAVE
A3: ADA
A4: ALGO
A5: APE
A6: APT
A7: ARB
A8: ASR
A9: AVAX
A10: AXS
A11: BCH
A12: BGB
... A47: XRP
